setup.py
swood/__init__.py
swood/complain.py
swood/instruments.py
swood/midiparse.py
swood/render.py
swood/sample.py
swood/soundfont.py
swood/wavout.py
swood.egg-info/PKG-INFO
swood.egg-info/SOURCES.txt
swood.egg-info/dependency_links.txt
swood.egg-info/entry_points.txt
swood.egg-info/requires.txt
swood.egg-info/top_level.txt