Metadata-Version: 1.1
Name: swood
Version: 1.0.4
Summary: With just one sample and a MIDI you too can make YTPMVs
Home-page: https://meme.institute/swood
Author: Milkey Mouse
Author-email: milkeymouse@meme.institute
License: MIT
Keywords: swood memes youtubepoop ytp ytpmvs
Platform: UNKNOWN
Classifier: Development Status :: 4 - Beta
Classifier: License :: OSI Approved :: MIT License
Classifier: Programming Language :: Python :: 3
Classifier: Programming Language :: Python :: 3.4
Classifier: Programming Language :: Python :: 3.5
